flask_rest_serializer/__init__.py
flask_rest_serializer/serializer.py
flask_rest_serializer/swagger.py
flask_rest_serializer-0.0.2.dist-info/LICENSE
flask_rest_serializer-0.0.2.dist-info/METADATA
flask_rest_serializer-0.0.2.dist-info/WHEEL
flask_rest_serializer-0.0.2.dist-info/top_level.txt
flask_rest_serializer-0.0.2.dist-info/RECORD
