Metadata-Version: 2.1
Name: flask-rest-serializer
Version: 0.0.2
Summary: Make it easy to serialize flask api request and response
Home-page: https://github.com/panjianjun/flask_rest_serializer
Author: bayi
Author-email: bayipan@gmail.com
License: Apache Software License
Keywords: flask rest serializer automatically swagger
Platform: UNKNOWN
Classifier: Development Status :: 4 - Beta
Classifier: Intended Audience :: Developers
Classifier: License :: OSI Approved :: Apache Software License
Classifier: Programming Language :: Python
Classifier: Programming Language :: Python :: 3
Classifier: Programming Language :: Python :: 3.6
Classifier: Programming Language :: Python :: 3.7
Classifier: Programming Language :: Python :: 3.8
Classifier: Programming Language :: Python :: 3.9
Classifier: Operating System :: OS Independent
Requires-Python: >=3.6
License-File: LICENSE
Requires-Dist: flask
Requires-Dist: marshmallow
Requires-Dist: apispec
Requires-Dist: pyyaml
